skypy/__init__.py
skypy/main.py
skypy_api-2.1.0.dist-info/LICENSE
skypy_api-2.1.0.dist-info/METADATA
skypy_api-2.1.0.dist-info/WHEEL
skypy_api-2.1.0.dist-info/top_level.txt
skypy_api-2.1.0.dist-info/RECORD
