Metadata-Version: 2.1
Name: skypy-api
Version: 2.1.0
Summary: Framework to connect to the Hypixel Skyblock API
Home-page: https://github.com/FuchsCrafter/skypy
Author: FuchsCrafter
License: GPL2
Classifier: Programming Language :: Python :: 3
Classifier: Operating System :: OS Independent
Requires-Python: >=3.7
License-File: LICENSE
Requires-Dist: requests
Requires-Dist: json
